qopstracker/__init__.py
q_ops_tracker_safaricom-0.0.3.1.dist-info/LICENCE.txt
q_ops_tracker_safaricom-0.0.3.1.dist-info/METADATA
q_ops_tracker_safaricom-0.0.3.1.dist-info/WHEEL
q_ops_tracker_safaricom-0.0.3.1.dist-info/top_level.txt
q_ops_tracker_safaricom-0.0.3.1.dist-info/RECORD
