Metadata-Version: 2.1
Name: q-ops-tracker-safaricom
Version: 0.0.3.1
Summary: Safaricom Q-OPS Automation tracker 
Author: Justus Mwangi Gitari (j_siri)
Author-email: mwangijustus12@gmail.com
License: MIT
Keywords: python,q-ops,safaricom,quality ops,quality engineering,tracker
Classifier: Development Status :: 5 - Production/Stable
Classifier: Intended Audience :: Developers
Classifier: Programming Language :: Python :: 3
Classifier: Operating System :: Unix
Classifier: Operating System :: MacOS :: MacOS X
Classifier: Operating System :: Microsoft :: Windows
License-File: LICENCE.txt
Requires-Dist: requests
Requires-Dist: robotframework
